dvsense_driver/__init__.py
dvsense_driver/__init__.pyi
dvsense_driver/avcodec-61.dll
dvsense_driver/avformat-61.dll
dvsense_driver/avutil-59.dll
dvsense_driver/base/__init__.py
dvsense_driver/base/__init__.pyi
dvsense_driver/calibrator.py
dvsense_driver/calibrator.pyi
dvsense_driver/camera_manager.py
dvsense_driver/camera_manager.pyi
dvsense_driver/dvs_aps_fusion_proccessor.py
dvsense_driver/dvs_aps_fusion_proccessor.pyi
dvsense_driver/dvs_camera.py
dvsense_driver/dvs_camera.pyi
dvsense_driver/dvs_fusion_camera.py
dvsense_driver/dvs_fusion_camera.pyi
dvsense_driver/dvsense_base_py.cp310-win_amd64.pyd
dvsense_driver/dvsense_driver_py.cp310-win_amd64.pyd
dvsense_driver/dvsense_hal_py.cp310-win_amd64.pyd
dvsense_driver/DvsenseBase.dll
dvsense_driver/DvsenseBase.lib
dvsense_driver/DvsenseDriver.dll
dvsense_driver/DvsenseDriver.lib
dvsense_driver/DvsenseHal.dll
dvsense_driver/DvsenseHal.lib
dvsense_driver/fmt.dll
dvsense_driver/hal/__init__.py
dvsense_driver/hal/camera_tool.py
dvsense_driver/hal/camera_tool.pyi
dvsense_driver/hal/dvs_camera_utils.py
dvsense_driver/hal/dvs_camera_utils.pyi
dvsense_driver/libusb-1.0.dll
dvsense_driver/mp4_file_reader.py
dvsense_driver/mp4_file_reader.pyi
dvsense_driver/raw_file_reader.py
dvsense_driver/raw_file_reader.pyi
dvsense_driver/spdlog.dll
dvsense_driver/swresample-5.dll
dvsense_driver/swscale-8.dll
share/dvsense_install_usb_driver.sh
dvsense_driver-1.1.6.dist-info/METADATA
dvsense_driver-1.1.6.dist-info/WHEEL
dvsense_driver-1.1.6.dist-info/RECORD
