Metadata-Version: 2.2
Name: dvsense_driver
Version: 1.1.6
Summary: Driver library for DVSense cameras)
Author-Email: Ziteng Wang <ziteng.wang@dvsense.com>, Xuanbin Wang <xuanbin.wang@dvsense.com>
Classifier: Programming Language :: Python :: 3
Classifier: Programming Language :: C++
Requires-Python: >=3.8
Requires-Dist: numpy>=1.20.0
